{
  "definitions": [
    {
      "title": "Sustainability Dashboard Achievement Matrix",
      "id": "sustainability-dashboard-achievement-matrix",
      "plugins": {
        "xwalk": {
          "page": {
            "resourceType": "core/franklin/components/block/v1/block/item",
            "template": {
              "name": "Sustainability Dashboard Achievement Matrix",
              "model": "sustainability-dashboard-achievement-matrix",
              "key-value": true
            }
          }
        }
      }
    }
  ],
  "models": [
    {
      "id": "sustainability-dashboard-achievement-matrix",
      "fields": [
        {
          "component": "text-input",
          "label": "",
          "name": "label-tag",
          "valueType":"string",
          "value": "matrix-label",
          "hidden": true
        },
        {
          "component": "text",
          "name": "matrix_label",
          "label": "Label",
          "valueType": "string"
        },
        {
          "component": "text-input",
          "label": "",
          "name": "value-tag",
          "valueType":"string",
          "value": "matrix-value",
          "hidden": true
        },
        {
          "component": "text",
          "name": "matrix_value",
          "label": "Value",
          "valueType": "string"
        }
      ]
    }
  ],
  "filters": []
}
